{"id":"3c7704f8-6d6d-49ba-803f-d3ef41ac435a","revision":0,"last_node_id":4,"last_link_id":4,"nodes":[{"id":1,"type":"PreviewAny","pos":[732.1234765562233,204.6109664352029],"size":[210,166],"flags":{},"order":1,"mode":0,"inputs":[{"localized_name":"源","name":"source","type":"*","link":3}],"outputs":[],"properties":{"cnr_id":"comfy-core","ver":"0.7.0","Node name for S&R":"PreviewAny","ue_properties":{"widget_ue_connectable":{},"input_ue_unconnectable":{},"version":"7.4.1"}},"widgets_values":[null,null,null]},{"id":2,"type":"PreviewAny","pos":[732.1234765562233,440.4801199055327],"size":[210,166],"flags":{},"order":2,"mode":0,"inputs":[{"localized_name":"源","name":"source","type":"*","link":4}],"outputs":[],"properties":{"cnr_id":"comfy-core","ver":"0.7.0","Node name for S&R":"PreviewAny","ue_properties":{"widget_ue_connectable":{},"input_ue_unconnectable":{},"version":"7.4.1"}},"widgets_values":[null,null,null]},{"id":4,"type":"HY-MT-Translator","pos":[264.9016729480483,204.6109664352029],"size":[400,288],"flags":{},"order":0,"mode":0,"inputs":[{"localized_name":"ckpt_name","name":"ckpt_name","type":"COMBO","widget":{"name":"ckpt_name"},"link":null},{"localized_name":"source_text","name":"source_text","type":"STRING","widget":{"name":"source_text"},"link":null},{"localized_name":"target_language","name":"target_language","type":"COMBO","widget":{"name":"target_language"},"link":null},{"localized_name":"prompt_template","name":"prompt_template","type":"STRING","widget":{"name":"prompt_template"},"link":null},{"localized_name":"regex_pattern","name":"regex_pattern","type":"STRING","widget":{"name":"regex_pattern"},"link":null},{"localized_name":"timeout","name":"timeout","type":"INT","widget":{"name":"timeout"},"link":null}],"outputs":[{"localized_name":"text","name":"text","type":"STRING","links":[3]},{"localized_name":"prompt_text","name":"prompt_text","type":"STRING","links":[4]}],"properties":{"Node name for S&R":"HY-MT-Translator","ue_properties":{"widget_ue_connectable":{},"input_ue_unconnectable":{},"version":"7.4.1"}},"widgets_values":["HY-MT1.5-1.8B-FP8","给云朵买香蕉","en - 英语","翻译：{source_text} -> {target_language}",":\\s*(.*?)$",30]}],"links":[[3,4,0,1,0,"STRING"],[4,4,1,2,0,"STRING"]],"groups":[],"config":{},"extra":{"workflowRendererVersion":"LG","ue_links":[],"ds":{"scale":0.45,"offset":[1668.4315968069989,655.5556703049658]},"links_added_by_ue":[]},"version":0.4}
